et3/__init__.py
et3/extract.py
et3/render.py
et3/utils.py
et3-1.5.2.dist-info/LICENCE.txt
et3-1.5.2.dist-info/METADATA
et3-1.5.2.dist-info/WHEEL
et3-1.5.2.dist-info/top_level.txt
et3-1.5.2.dist-info/RECORD
