Metadata-Version: 2.1
Name: et3
Version: 1.5.2
Summary: Simple library for Extracting and Transforming data, third incarnation.
Home-page: https://github.com/lsh-0/et3
Download-URL: https://github.com/lsh-0/et3/archive/refs/tags/1.5.2.tar.gz
Author: Luke
Author-email: lsh-0@users.noreply.github.com
License: GPLv3
Platform: any
Classifier: Programming Language :: Python :: 2
Classifier: Programming Language :: Python :: 3
Classifier: Development Status :: 5 - Production/Stable
Classifier: Intended Audience :: Developers
Classifier: License :: OSI Approved :: GNU General Public License v3 or later (GPLv3+)
License-File: LICENCE.txt
